{
  "timestamp": "20250117_053920",
  "datetime": "2025-01-17T05:39:20.391975",
  "total_markets": 159,
  "statistics": {
    "highest_rate": {
      "symbol": "GRIFFAIN/USDC:USDC",
      "rate": 0.00017102,
      "rate_pct": 0.017102
    },
    "lowest_rate": {
      "symbol": "TURBO/USDC:USDC",
      "rate": -2.49e-06,
      "rate_pct": -0.000249
    },
    "mean_rate": 1.3980314465408806e-05,
    "median_rate": 1.25e-05
  },
  "rates": [
    {
      "symbol": "GRIFFAIN/USDC:USDC",
      "funding_rate": 0.00017102,
      "funding_rate_pct": 0.017102,
      "datetime": null,
      "timestamp": 1737072382279,
      "prediction_price": 0.002954
    },
    {
      "symbol": "ONDO/USDC:USDC",
      "funding_rate": -0.00013953,
      "funding_rate_pct": -0.013952999999999998,
      "datetime": null,
      "timestamp": 1737072382279,
      "prediction_price": -0.00180372
    },
    {
      "symbol": "BADGER/USDC:USDC",
      "funding_rate": -0.00010762,
      "funding_rate_pct": -0.010762,
      "datetime": null,
      "timestamp": 1737072382279,
      "prediction_price": -0.0004351
    },
    {
      "symbol": "FARTCOIN/USDC:USDC",
      "funding_rate": 8.241e-05,
      "funding_rate_pct": 0.008241,
      "datetime": null,
      "timestamp": 1737072382279,
      "prediction_price": 0.00040762
    },
    {
      "symbol": "SUI/USDC:USDC",
      "funding_rate": 7.46e-05,
      "funding_rate_pct": 0.00746,
      "datetime": null,
      "timestamp": 1737072382279,
      "prediction_price": 0.0008606
    },
    {
      "symbol": "POPCAT/USDC:USDC",
      "funding_rate": 6.316e-05,
      "funding_rate_pct": 0.0063159999999999996,
      "datetime": null,
      "timestamp": 1737072382279,
      "prediction_price": 0.00106392
    },
    {
      "symbol": "kBONK/USDC:USDC",
      "funding_rate": 6.24e-05,
      "funding_rate_pct": 0.00624,
      "datetime": null,
      "timestamp": 1737072382279,
      "prediction_price": 0.001123
    },
    {
      "symbol": "AI16Z/USDC:USDC",
      "funding_rate": 6.043e-05,
      "funding_rate_pct": 0.006043000000000001,
      "datetime": null,
      "timestamp": 1737072382279,
      "prediction_price": 0.00082739
    },
    {
      "symbol": "PENGU/USDC:USDC",
      "funding_rate": 5.363e-05,
      "funding_rate_pct": 0.005363,
      "datetime": null,
      "timestamp": 1737072382279,
      "prediction_price": 0.00051869
    },
    {
      "symbol": "KAS/USDC:USDC",
      "funding_rate": 4.552e-05,
      "funding_rate_pct": 0.004552,
      "datetime": null,
      "timestamp": 1737072382279,
      "prediction_price": 0.00092416
    },
    {
      "symbol": "kPEPE/USDC:USDC",
      "funding_rate": 4.074e-05,
      "funding_rate_pct": 0.004074,
      "datetime": null,
      "timestamp": 1737072382279,
      "prediction_price": 0.00071448
    },
    {
      "symbol": "ZEREBRO/USDC:USDC",
      "funding_rate": 3.785e-05,
      "funding_rate_pct": 0.0037849999999999997,
      "datetime": null,
      "timestamp": 1737072382279,
      "prediction_price": 0.00134055
    },
    {
      "symbol": "JUP/USDC:USDC",
      "funding_rate": -3.378e-05,
      "funding_rate_pct": -0.003378,
      "datetime": null,
      "timestamp": 1737072382279,
      "prediction_price": -0.00085497
    },
    {
      "symbol": "BIO/USDC:USDC",
      "funding_rate": 3.27e-05,
      "funding_rate_pct": 0.0032700000000000003,
      "datetime": null,
      "timestamp": 1737072382279,
      "prediction_price": 0.00081088
    },
    {
      "symbol": "SUPER/USDC:USDC",
      "funding_rate": 2.815e-05,
      "funding_rate_pct": 0.002815,
      "datetime": null,
      "timestamp": 1737072382279,
      "prediction_price": 0.00076753
    },
    {
      "symbol": "MYRO/USDC:USDC",
      "funding_rate": 2.712e-05,
      "funding_rate_pct": 0.002712,
      "datetime": null,
      "timestamp": 1737072382279,
      "prediction_price": 0.00066376
    },
    {
      "symbol": "CRV/USDC:USDC",
      "funding_rate": 2.388e-05,
      "funding_rate_pct": 0.002388,
      "datetime": null,
      "timestamp": 1737072382279,
      "prediction_price": 0.00031093
    },
    {
      "symbol": "GMT/USDC:USDC",
      "funding_rate": -2.245e-05,
      "funding_rate_pct": -0.002245,
      "datetime": null,
      "timestamp": 1737072382279,
      "prediction_price": -0.00105535
    },
    {
      "symbol": "HYPE/USDC:USDC",
      "funding_rate": 2.22e-05,
      "funding_rate_pct": 0.00222,
      "datetime": null,
      "timestamp": 1737072382279,
      "prediction_price": 0.00093569
    },
    {
      "symbol": "ETHFI/USDC:USDC",
      "funding_rate": 2.052e-05,
      "funding_rate_pct": 0.002052,
      "datetime": null,
      "timestamp": 1737072382279,
      "prediction_price": 0.00108082
    },
    {
      "symbol": "USUAL/USDC:USDC",
      "funding_rate": -1.867e-05,
      "funding_rate_pct": -0.001867,
      "datetime": null,
      "timestamp": 1737072382279,
      "prediction_price": -0.00031669
    },
    {
      "symbol": "SOL/USDC:USDC",
      "funding_rate": 1.822e-05,
      "funding_rate_pct": 0.0018219999999999998,
      "datetime": null,
      "timestamp": 1737072382279,
      "prediction_price": 0.00071019
    },
    {
      "symbol": "WLD/USDC:USDC",
      "funding_rate": 1.342e-05,
      "funding_rate_pct": 0.001342,
      "datetime": null,
      "timestamp": 1737072382279,
      "prediction_price": 0.00051448
    },
    {
      "symbol": "MNT/USDC:USDC",
      "funding_rate": 1.25e-05,
      "funding_rate_pct": 0.00125,
      "datetime": null,
      "timestamp": 1737072382279,
      "prediction_price": 0.00012484
    },
    {
      "symbol": "AR/USDC:USDC",
      "funding_rate": 1.25e-05,
      "funding_rate_pct": 0.00125,
      "datetime": null,
      "timestamp": 1737072382279,
      "prediction_price": 0.00052466
    },
    {
      "symbol": "AI/USDC:USDC",
      "funding_rate": 1.25e-05,
      "funding_rate_pct": 0.00125,
      "datetime": null,
      "timestamp": 1737072382279,
      "prediction_price": 0.00049826
    },
    {
      "symbol": "TAO/USDC:USDC",
      "funding_rate": 1.25e-05,
      "funding_rate_pct": 0.00125,
      "datetime": null,
      "timestamp": 1737072382279,
      "prediction_price": 0.00023889
    },
    {
      "symbol": "BOME/USDC:USDC",
      "funding_rate": 1.25e-05,
      "funding_rate_pct": 0.00125,
      "datetime": null,
      "timestamp": 1737072382279,
      "prediction_price": 0.0
    },
    {
      "symbol": "kFLOKI/USDC:USDC",
      "funding_rate": 1.25e-05,
      "funding_rate_pct": 0.00125,
      "datetime": null,
      "timestamp": 1737072382279,
      "prediction_price": 0.0
    },
    {
      "symbol": "SAGA/USDC:USDC",
      "funding_rate": 1.25e-05,
      "funding_rate_pct": 0.00125,
      "datetime": null,
      "timestamp": 1737072382279,
      "prediction_price": 0.0
    },
    {
      "symbol": "ENA/USDC:USDC",
      "funding_rate": 1.25e-05,
      "funding_rate_pct": 0.00125,
      "datetime": null,
      "timestamp": 1737072382279,
      "prediction_price": -0.00043393
    },
    {
      "symbol": "STRK/USDC:USDC",
      "funding_rate": 1.25e-05,
      "funding_rate_pct": 0.00125,
      "datetime": null,
      "timestamp": 1737072382279,
      "prediction_price": -0.00021186
    },
    {
      "symbol": "PIXEL/USDC:USDC",
      "funding_rate": 1.25e-05,
      "funding_rate_pct": 0.00125,
      "datetime": null,
      "timestamp": 1737072382279,
      "prediction_price": -0.00014693
    },
    {
      "symbol": "BTC/USDC:USDC",
      "funding_rate": 1.25e-05,
      "funding_rate_pct": 0.00125,
      "datetime": null,
      "timestamp": 1737072382279,
      "prediction_price": 0.00046947
    },
    {
      "symbol": "W/USDC:USDC",
      "funding_rate": 1.25e-05,
      "funding_rate_pct": 0.00125,
      "datetime": null,
      "timestamp": 1737072382279,
      "prediction_price": 0.00011601
    },
    {
      "symbol": "MAVIA/USDC:USDC",
      "funding_rate": 1.25e-05,
      "funding_rate_pct": 0.00125,
      "datetime": null,
      "timestamp": 1737072382279,
      "prediction_price": 0.0
    },
    {
      "symbol": "DYM/USDC:USDC",
      "funding_rate": 1.25e-05,
      "funding_rate_pct": 0.00125,
      "datetime": null,
      "timestamp": 1737072382279,
      "prediction_price": 0.0
    },
    {
      "symbol": "ZETA/USDC:USDC",
      "funding_rate": 1.25e-05,
      "funding_rate_pct": 0.00125,
      "datetime": null,
      "timestamp": 1737072382279,
      "prediction_price": 0.0
    },
    {
      "symbol": "ALT/USDC:USDC",
      "funding_rate": 1.25e-05,
      "funding_rate_pct": 0.00125,
      "datetime": null,
      "timestamp": 1737072382279,
      "prediction_price": 0.0
    },
    {
      "symbol": "UMA/USDC:USDC",
      "funding_rate": 1.25e-05,
      "funding_rate_pct": 0.00125,
      "datetime": null,
      "timestamp": 1737072382279,
      "prediction_price": -0.00074205
    },
    {
      "symbol": "MERL/USDC:USDC",
      "funding_rate": 1.25e-05,
      "funding_rate_pct": 0.00125,
      "datetime": null,
      "timestamp": 1737072382279,
      "prediction_price": 0.0
    },
    {
      "symbol": "XAI/USDC:USDC",
      "funding_rate": 1.25e-05,
      "funding_rate_pct": 0.00125,
      "datetime": null,
      "timestamp": 1737072382279,
      "prediction_price": 0.0
    },
    {
      "symbol": "ETC/USDC:USDC",
      "funding_rate": 1.25e-05,
      "funding_rate_pct": 0.00125,
      "datetime": null,
      "timestamp": 1737072382279,
      "prediction_price": -0.0001492
    },
    {
      "symbol": "ENS/USDC:USDC",
      "funding_rate": 1.25e-05,
      "funding_rate_pct": 0.00125,
      "datetime": null,
      "timestamp": 1737072382279,
      "prediction_price": 0.0
    },
    {
      "symbol": "PEOPLE/USDC:USDC",
      "funding_rate": 1.25e-05,
      "funding_rate_pct": 0.00125,
      "datetime": null,
      "timestamp": 1737072382279,
      "prediction_price": 0.0
    },
    {
      "symbol": "CAKE/USDC:USDC",
      "funding_rate": 1.25e-05,
      "funding_rate_pct": 0.00125,
      "datetime": null,
      "timestamp": 1737072382279,
      "prediction_price": 0.0
    },
    {
      "symbol": "WIF/USDC:USDC",
      "funding_rate": 1.25e-05,
      "funding_rate_pct": 0.00125,
      "datetime": null,
      "timestamp": 1737072382279,
      "prediction_price": 0.00013848
    },
    {
      "symbol": "MANTA/USDC:USDC",
      "funding_rate": 1.25e-05,
      "funding_rate_pct": 0.00125,
      "datetime": null,
      "timestamp": 1737072382279,
      "prediction_price": -0.00065531
    },
    {
      "symbol": "ZK/USDC:USDC",
      "funding_rate": 1.25e-05,
      "funding_rate_pct": 0.00125,
      "datetime": null,
      "timestamp": 1737072382279,
      "prediction_price": 0.0
    },
    {
      "symbol": "HBAR/USDC:USDC",
      "funding_rate": 1.25e-05,
      "funding_rate_pct": 0.00125,
      "datetime": null,
      "timestamp": 1737072382279,
      "prediction_price": 0.0004977
    },
    {
      "symbol": "CHILLGUY/USDC:USDC",
      "funding_rate": 1.25e-05,
      "funding_rate_pct": 0.00125,
      "datetime": null,
      "timestamp": 1737072382279,
      "prediction_price": 0.00031001
    },
    {
      "symbol": "GOAT/USDC:USDC",
      "funding_rate": 1.25e-05,
      "funding_rate_pct": 0.00125,
      "datetime": null,
      "timestamp": 1737072382279,
      "prediction_price": 0.00013018
    },
    {
      "symbol": "MOODENG/USDC:USDC",
      "funding_rate": 1.25e-05,
      "funding_rate_pct": 0.00125,
      "datetime": null,
      "timestamp": 1737072382279,
      "prediction_price": 0.0
    },
    {
      "symbol": "GRASS/USDC:USDC",
      "funding_rate": 1.25e-05,
      "funding_rate_pct": 0.00125,
      "datetime": null,
      "timestamp": 1737072382279,
      "prediction_price": 0.00021346
    },
    {
      "symbol": "PURR/USDC:USDC",
      "funding_rate": 1.25e-05,
      "funding_rate_pct": 0.00125,
      "datetime": null,
      "timestamp": 1737072382279,
      "prediction_price": 0.0
    },
    {
      "symbol": "PNUT/USDC:USDC",
      "funding_rate": 1.25e-05,
      "funding_rate_pct": 0.00125,
      "datetime": null,
      "timestamp": 1737072382279,
      "prediction_price": 0.00026689
    },
    {
      "symbol": "XLM/USDC:USDC",
      "funding_rate": 1.25e-05,
      "funding_rate_pct": 0.00125,
      "datetime": null,
      "timestamp": 1737072382279,
      "prediction_price": 0.0
    },
    {
      "symbol": "SAND/USDC:USDC",
      "funding_rate": 1.25e-05,
      "funding_rate_pct": 0.00125,
      "datetime": null,
      "timestamp": 1737072382279,
      "prediction_price": 0.0
    },
    {
      "symbol": "OMNI/USDC:USDC",
      "funding_rate": 1.25e-05,
      "funding_rate_pct": 0.00125,
      "datetime": null,
      "timestamp": 1737072382279,
      "prediction_price": 0.0
    },
    {
      "symbol": "IOTA/USDC:USDC",
      "funding_rate": 1.25e-05,
      "funding_rate_pct": 0.00125,
      "datetime": null,
      "timestamp": 1737072382279,
      "prediction_price": 0.0
    },
    {
      "symbol": "ALGO/USDC:USDC",
      "funding_rate": 1.25e-05,
      "funding_rate_pct": 0.00125,
      "datetime": null,
      "timestamp": 1737072382279,
      "prediction_price": 0.00022713
    },
    {
      "symbol": "ME/USDC:USDC",
      "funding_rate": 1.25e-05,
      "funding_rate_pct": 0.00125,
      "datetime": null,
      "timestamp": 1737072382279,
      "prediction_price": 0.00010481
    },
    {
      "symbol": "MOVE/USDC:USDC",
      "funding_rate": 1.25e-05,
      "funding_rate_pct": 0.00125,
      "datetime": null,
      "timestamp": 1737072382279,
      "prediction_price": 0.0
    },
    {
      "symbol": "VIRTUAL/USDC:USDC",
      "funding_rate": 1.25e-05,
      "funding_rate_pct": 0.00125,
      "datetime": null,
      "timestamp": 1737072382279,
      "prediction_price": 0.00075602
    },
    {
      "symbol": "AIXBT/USDC:USDC",
      "funding_rate": 1.25e-05,
      "funding_rate_pct": 0.00125,
      "datetime": null,
      "timestamp": 1737072382279,
      "prediction_price": 0.00052409
    },
    {
      "symbol": "kNEIRO/USDC:USDC",
      "funding_rate": 1.25e-05,
      "funding_rate_pct": 0.00125,
      "datetime": null,
      "timestamp": 1737072382279,
      "prediction_price": -7.499e-05
    },
    {
      "symbol": "NEIROETH/USDC:USDC",
      "funding_rate": 1.25e-05,
      "funding_rate_pct": 0.00125,
      "datetime": null,
      "timestamp": 1737072382279,
      "prediction_price": 0.00053333
    },
    {
      "symbol": "SCR/USDC:USDC",
      "funding_rate": 1.25e-05,
      "funding_rate_pct": 0.00125,
      "datetime": null,
      "timestamp": 1737072382279,
      "prediction_price": 0.0
    },
    {
      "symbol": "HMSTR/USDC:USDC",
      "funding_rate": 1.25e-05,
      "funding_rate_pct": 0.00125,
      "datetime": null,
      "timestamp": 1737072382279,
      "prediction_price": 0.0
    },
    {
      "symbol": "CELO/USDC:USDC",
      "funding_rate": 1.25e-05,
      "funding_rate_pct": 0.00125,
      "datetime": null,
      "timestamp": 1737072382279,
      "prediction_price": -0.00017413
    },
    {
      "symbol": "CATI/USDC:USDC",
      "funding_rate": 1.25e-05,
      "funding_rate_pct": 0.00125,
      "datetime": null,
      "timestamp": 1737072382279,
      "prediction_price": 0.0
    },
    {
      "symbol": "POL/USDC:USDC",
      "funding_rate": 1.25e-05,
      "funding_rate_pct": 0.00125,
      "datetime": null,
      "timestamp": 1737072382279,
      "prediction_price": 0.0
    },
    {
      "symbol": "kDOGS/USDC:USDC",
      "funding_rate": 1.25e-05,
      "funding_rate_pct": 0.00125,
      "datetime": null,
      "timestamp": 1737072382279,
      "prediction_price": 0.0
    },
    {
      "symbol": "RENDER/USDC:USDC",
      "funding_rate": 1.25e-05,
      "funding_rate_pct": 0.00125,
      "datetime": null,
      "timestamp": 1737072382279,
      "prediction_price": 0.00058083
    },
    {
      "symbol": "MEW/USDC:USDC",
      "funding_rate": 1.25e-05,
      "funding_rate_pct": 0.00125,
      "datetime": null,
      "timestamp": 1737072382279,
      "prediction_price": 0.0
    },
    {
      "symbol": "LISTA/USDC:USDC",
      "funding_rate": 1.25e-05,
      "funding_rate_pct": 0.00125,
      "datetime": null,
      "timestamp": 1737072382279,
      "prediction_price": -0.00014156
    },
    {
      "symbol": "BLAST/USDC:USDC",
      "funding_rate": 1.25e-05,
      "funding_rate_pct": 0.00125,
      "datetime": null,
      "timestamp": 1737072382279,
      "prediction_price": -0.00022686
    },
    {
      "symbol": "ACE/USDC:USDC",
      "funding_rate": 1.25e-05,
      "funding_rate_pct": 0.00125,
      "datetime": null,
      "timestamp": 1737072382279,
      "prediction_price": 0.0
    },
    {
      "symbol": "BRETT/USDC:USDC",
      "funding_rate": 1.25e-05,
      "funding_rate_pct": 0.00125,
      "datetime": null,
      "timestamp": 1737072382279,
      "prediction_price": 0.00089693
    },
    {
      "symbol": "NOT/USDC:USDC",
      "funding_rate": 1.25e-05,
      "funding_rate_pct": 0.00125,
      "datetime": null,
      "timestamp": 1737072382279,
      "prediction_price": 0.00016364
    },
    {
      "symbol": "REZ/USDC:USDC",
      "funding_rate": 1.25e-05,
      "funding_rate_pct": 0.00125,
      "datetime": null,
      "timestamp": 1737072382279,
      "prediction_price": 0.0
    },
    {
      "symbol": "EIGEN/USDC:USDC",
      "funding_rate": 1.25e-05,
      "funding_rate_pct": 0.00125,
      "datetime": null,
      "timestamp": 1737072382279,
      "prediction_price": 0.00073294
    },
    {
      "symbol": "MAV/USDC:USDC",
      "funding_rate": 1.25e-05,
      "funding_rate_pct": 0.00125,
      "datetime": null,
      "timestamp": 1737072382279,
      "prediction_price": 0.0
    },
    {
      "symbol": "kLUNC/USDC:USDC",
      "funding_rate": 1.25e-05,
      "funding_rate_pct": 0.00125,
      "datetime": null,
      "timestamp": 1737072382279,
      "prediction_price": 0.0
    },
    {
      "symbol": "NTRN/USDC:USDC",
      "funding_rate": 1.25e-05,
      "funding_rate_pct": 0.00125,
      "datetime": null,
      "timestamp": 1737072382279,
      "prediction_price": 0.0
    },
    {
      "symbol": "BCH/USDC:USDC",
      "funding_rate": 1.25e-05,
      "funding_rate_pct": 0.00125,
      "datetime": null,
      "timestamp": 1737072382279,
      "prediction_price": 0.00028148
    },
    {
      "symbol": "AAVE/USDC:USDC",
      "funding_rate": 1.25e-05,
      "funding_rate_pct": 0.00125,
      "datetime": null,
      "timestamp": 1737072382279,
      "prediction_price": 0.00016018
    },
    {
      "symbol": "COMP/USDC:USDC",
      "funding_rate": 1.25e-05,
      "funding_rate_pct": 0.00125,
      "datetime": null,
      "timestamp": 1737072382279,
      "prediction_price": -0.00026539
    },
    {
      "symbol": "MKR/USDC:USDC",
      "funding_rate": 1.25e-05,
      "funding_rate_pct": 0.00125,
      "datetime": null,
      "timestamp": 1737072382279,
      "prediction_price": 0.0
    },
    {
      "symbol": "FXS/USDC:USDC",
      "funding_rate": 1.25e-05,
      "funding_rate_pct": 0.00125,
      "datetime": null,
      "timestamp": 1737072382279,
      "prediction_price": 0.0
    },
    {
      "symbol": "HPOS/USDC:USDC",
      "funding_rate": 1.25e-05,
      "funding_rate_pct": 0.00125,
      "datetime": null,
      "timestamp": 1737072382279,
      "prediction_price": 0.0
    },
    {
      "symbol": "RLB/USDC:USDC",
      "funding_rate": 1.25e-05,
      "funding_rate_pct": 0.00125,
      "datetime": null,
      "timestamp": 1737072382279,
      "prediction_price": 0.0
    },
    {
      "symbol": "YGG/USDC:USDC",
      "funding_rate": 1.25e-05,
      "funding_rate_pct": 0.00125,
      "datetime": null,
      "timestamp": 1737072382279,
      "prediction_price": -0.00030353
    },
    {
      "symbol": "TRX/USDC:USDC",
      "funding_rate": 1.25e-05,
      "funding_rate_pct": 0.00125,
      "datetime": null,
      "timestamp": 1737072382279,
      "prediction_price": 0.0
    },
    {
      "symbol": "kSHIB/USDC:USDC",
      "funding_rate": 1.25e-05,
      "funding_rate_pct": 0.00125,
      "datetime": null,
      "timestamp": 1737072382279,
      "prediction_price": 0.00022631
    },
    {
      "symbol": "UNI/USDC:USDC",
      "funding_rate": 1.25e-05,
      "funding_rate_pct": 0.00125,
      "datetime": null,
      "timestamp": 1737072382279,
      "prediction_price": 0.00055979
    },
    {
      "symbol": "SEI/USDC:USDC",
      "funding_rate": 1.25e-05,
      "funding_rate_pct": 0.00125,
      "datetime": null,
      "timestamp": 1737072382279,
      "prediction_price": 0.0
    },
    {
      "symbol": "RUNE/USDC:USDC",
      "funding_rate": 1.25e-05,
      "funding_rate_pct": 0.00125,
      "datetime": null,
      "timestamp": 1737072382279,
      "prediction_price": 0.00022617
    },
    {
      "symbol": "CYBER/USDC:USDC",
      "funding_rate": 1.25e-05,
      "funding_rate_pct": 0.00125,
      "datetime": null,
      "timestamp": 1737072382279,
      "prediction_price": 0.0
    },
    {
      "symbol": "ZRO/USDC:USDC",
      "funding_rate": 1.25e-05,
      "funding_rate_pct": 0.00125,
      "datetime": null,
      "timestamp": 1737072382279,
      "prediction_price": 0.0006029
    },
    {
      "symbol": "DOT/USDC:USDC",
      "funding_rate": 1.25e-05,
      "funding_rate_pct": 0.00125,
      "datetime": null,
      "timestamp": 1737072382279,
      "prediction_price": 0.0
    },
    {
      "symbol": "APT/USDC:USDC",
      "funding_rate": 1.25e-05,
      "funding_rate_pct": 0.00125,
      "datetime": null,
      "timestamp": 1737072382279,
      "prediction_price": 0.00044081
    },
    {
      "symbol": "XRP/USDC:USDC",
      "funding_rate": 1.25e-05,
      "funding_rate_pct": 0.00125,
      "datetime": null,
      "timestamp": 1737072382279,
      "prediction_price": 0.00018277
    },
    {
      "symbol": "JTO/USDC:USDC",
      "funding_rate": 1.25e-05,
      "funding_rate_pct": 0.00125,
      "datetime": null,
      "timestamp": 1737072382279,
      "prediction_price": 4.248e-05
    },
    {
      "symbol": "SNX/USDC:USDC",
      "funding_rate": 1.25e-05,
      "funding_rate_pct": 0.00125,
      "datetime": null,
      "timestamp": 1737072382279,
      "prediction_price": -0.00028017
    },
    {
      "symbol": "ATOM/USDC:USDC",
      "funding_rate": 1.25e-05,
      "funding_rate_pct": 0.00125,
      "datetime": null,
      "timestamp": 1737072382279,
      "prediction_price": -6.036e-05
    },
    {
      "symbol": "DYDX/USDC:USDC",
      "funding_rate": 1.25e-05,
      "funding_rate_pct": 0.00125,
      "datetime": null,
      "timestamp": 1737072382279,
      "prediction_price": 0.0
    },
    {
      "symbol": "AVAX/USDC:USDC",
      "funding_rate": 1.25e-05,
      "funding_rate_pct": 0.00125,
      "datetime": null,
      "timestamp": 1737072382279,
      "prediction_price": 0.00014919
    },
    {
      "symbol": "BNB/USDC:USDC",
      "funding_rate": 1.25e-05,
      "funding_rate_pct": 0.00125,
      "datetime": null,
      "timestamp": 1737072382279,
      "prediction_price": 0.00030999
    },
    {
      "symbol": "APE/USDC:USDC",
      "funding_rate": 1.25e-05,
      "funding_rate_pct": 0.00125,
      "datetime": null,
      "timestamp": 1737072382279,
      "prediction_price": 0.0
    },
    {
      "symbol": "OP/USDC:USDC",
      "funding_rate": 1.25e-05,
      "funding_rate_pct": 0.00125,
      "datetime": null,
      "timestamp": 1737072382279,
      "prediction_price": 0.00021719
    },
    {
      "symbol": "LTC/USDC:USDC",
      "funding_rate": 1.25e-05,
      "funding_rate_pct": 0.00125,
      "datetime": null,
      "timestamp": 1737072382279,
      "prediction_price": 0.00060824
    },
    {
      "symbol": "ARB/USDC:USDC",
      "funding_rate": 1.25e-05,
      "funding_rate_pct": 0.00125,
      "datetime": null,
      "timestamp": 1737072382279,
      "prediction_price": 0.00032884
    },
    {
      "symbol": "DOGE/USDC:USDC",
      "funding_rate": 1.25e-05,
      "funding_rate_pct": 0.00125,
      "datetime": null,
      "timestamp": 1737072382279,
      "prediction_price": 0.00047376
    },
    {
      "symbol": "INJ/USDC:USDC",
      "funding_rate": 1.25e-05,
      "funding_rate_pct": 0.00125,
      "datetime": null,
      "timestamp": 1737072382279,
      "prediction_price": 0.00024489
    },
    {
      "symbol": "LDO/USDC:USDC",
      "funding_rate": 1.25e-05,
      "funding_rate_pct": 0.00125,
      "datetime": null,
      "timestamp": 1737072382279,
      "prediction_price": 0.0
    },
    {
      "symbol": "LINK/USDC:USDC",
      "funding_rate": 1.25e-05,
      "funding_rate_pct": 0.00125,
      "datetime": null,
      "timestamp": 1737072382279,
      "prediction_price": 0.00057506
    },
    {
      "symbol": "STX/USDC:USDC",
      "funding_rate": 1.25e-05,
      "funding_rate_pct": 0.00125,
      "datetime": null,
      "timestamp": 1737072382279,
      "prediction_price": 0.0
    },
    {
      "symbol": "CFX/USDC:USDC",
      "funding_rate": 1.25e-05,
      "funding_rate_pct": 0.00125,
      "datetime": null,
      "timestamp": 1737072382279,
      "prediction_price": -1.772e-05
    },
    {
      "symbol": "GMX/USDC:USDC",
      "funding_rate": 1.25e-05,
      "funding_rate_pct": 0.00125,
      "datetime": null,
      "timestamp": 1737072382279,
      "prediction_price": 0.0
    },
    {
      "symbol": "BANANA/USDC:USDC",
      "funding_rate": 1.25e-05,
      "funding_rate_pct": 0.00125,
      "datetime": null,
      "timestamp": 1737072382279,
      "prediction_price": 0.0
    },
    {
      "symbol": "TRB/USDC:USDC",
      "funding_rate": 1.25e-05,
      "funding_rate_pct": 0.00125,
      "datetime": null,
      "timestamp": 1737072382279,
      "prediction_price": 0.0
    },
    {
      "symbol": "GAS/USDC:USDC",
      "funding_rate": 1.25e-05,
      "funding_rate_pct": 0.00125,
      "datetime": null,
      "timestamp": 1737072382279,
      "prediction_price": -3.408e-05
    },
    {
      "symbol": "PENDLE/USDC:USDC",
      "funding_rate": 1.25e-05,
      "funding_rate_pct": 0.00125,
      "datetime": null,
      "timestamp": 1737072382279,
      "prediction_price": 0.000552
    },
    {
      "symbol": "FET/USDC:USDC",
      "funding_rate": 1.25e-05,
      "funding_rate_pct": 0.00125,
      "datetime": null,
      "timestamp": 1737072382279,
      "prediction_price": 0.00015327
    },
    {
      "symbol": "NEAR/USDC:USDC",
      "funding_rate": 1.25e-05,
      "funding_rate_pct": 0.00125,
      "datetime": null,
      "timestamp": 1737072382279,
      "prediction_price": 0.0
    },
    {
      "symbol": "MEME/USDC:USDC",
      "funding_rate": 1.25e-05,
      "funding_rate_pct": 0.00125,
      "datetime": null,
      "timestamp": 1737072382279,
      "prediction_price": 0.0
    },
    {
      "symbol": "ORDI/USDC:USDC",
      "funding_rate": 1.25e-05,
      "funding_rate_pct": 0.00125,
      "datetime": null,
      "timestamp": 1737072382279,
      "prediction_price": 0.00072617
    },
    {
      "symbol": "NEO/USDC:USDC",
      "funding_rate": 1.25e-05,
      "funding_rate_pct": 0.00125,
      "datetime": null,
      "timestamp": 1737072382279,
      "prediction_price": 0.0
    },
    {
      "symbol": "ZEN/USDC:USDC",
      "funding_rate": 1.25e-05,
      "funding_rate_pct": 0.00125,
      "datetime": null,
      "timestamp": 1737072382279,
      "prediction_price": 0.0
    },
    {
      "symbol": "FIL/USDC:USDC",
      "funding_rate": 1.25e-05,
      "funding_rate_pct": 0.00125,
      "datetime": null,
      "timestamp": 1737072382279,
      "prediction_price": 0.0
    },
    {
      "symbol": "PYTH/USDC:USDC",
      "funding_rate": 1.25e-05,
      "funding_rate_pct": 0.00125,
      "datetime": null,
      "timestamp": 1737072382279,
      "prediction_price": 9.196e-05
    },
    {
      "symbol": "SUSHI/USDC:USDC",
      "funding_rate": 1.25e-05,
      "funding_rate_pct": 0.00125,
      "datetime": null,
      "timestamp": 1737072382279,
      "prediction_price": 0.0
    },
    {
      "symbol": "ILV/USDC:USDC",
      "funding_rate": 1.25e-05,
      "funding_rate_pct": 0.00125,
      "datetime": null,
      "timestamp": 1737072382279,
      "prediction_price": 0.00014566
    },
    {
      "symbol": "IMX/USDC:USDC",
      "funding_rate": 1.25e-05,
      "funding_rate_pct": 0.00125,
      "datetime": null,
      "timestamp": 1737072382279,
      "prediction_price": 0.0
    },
    {
      "symbol": "USTC/USDC:USDC",
      "funding_rate": 1.25e-05,
      "funding_rate_pct": 0.00125,
      "datetime": null,
      "timestamp": 1737072382279,
      "prediction_price": 0.0
    },
    {
      "symbol": "ETH/USDC:USDC",
      "funding_rate": 1.25e-05,
      "funding_rate_pct": 0.00125,
      "datetime": null,
      "timestamp": 1737072382279,
      "prediction_price": 0.00041966
    },
    {
      "symbol": "RSR/USDC:USDC",
      "funding_rate": 1.25e-05,
      "funding_rate_pct": 0.00125,
      "datetime": null,
      "timestamp": 1737072382279,
      "prediction_price": 6.922e-05
    },
    {
      "symbol": "GALA/USDC:USDC",
      "funding_rate": 1.25e-05,
      "funding_rate_pct": 0.00125,
      "datetime": null,
      "timestamp": 1737072382279,
      "prediction_price": 0.0
    },
    {
      "symbol": "STG/USDC:USDC",
      "funding_rate": 1.25e-05,
      "funding_rate_pct": 0.00125,
      "datetime": null,
      "timestamp": 1737072382279,
      "prediction_price": -0.00020015
    },
    {
      "symbol": "SPX/USDC:USDC",
      "funding_rate": 1.25e-05,
      "funding_rate_pct": 0.00125,
      "datetime": null,
      "timestamp": 1737072382279,
      "prediction_price": 0.0
    },
    {
      "symbol": "ORBS/USDC:USDC",
      "funding_rate": 1.25e-05,
      "funding_rate_pct": 0.00125,
      "datetime": null,
      "timestamp": 1737072382279,
      "prediction_price": 0.0
    },
    {
      "symbol": "FTT/USDC:USDC",
      "funding_rate": 1.25e-05,
      "funding_rate_pct": 0.00125,
      "datetime": null,
      "timestamp": 1737072382279,
      "prediction_price": 0.0
    },
    {
      "symbol": "MINA/USDC:USDC",
      "funding_rate": 1.25e-05,
      "funding_rate_pct": 0.00125,
      "datetime": null,
      "timestamp": 1737072382279,
      "prediction_price": 0.0
    },
    {
      "symbol": "TON/USDC:USDC",
      "funding_rate": 1.25e-05,
      "funding_rate_pct": 0.00125,
      "datetime": null,
      "timestamp": 1737072382279,
      "prediction_price": -0.00014026
    },
    {
      "symbol": "ADA/USDC:USDC",
      "funding_rate": 1.25e-05,
      "funding_rate_pct": 0.00125,
      "datetime": null,
      "timestamp": 1737072382279,
      "prediction_price": 0.00025531
    },
    {
      "symbol": "BSV/USDC:USDC",
      "funding_rate": 1.25e-05,
      "funding_rate_pct": 0.00125,
      "datetime": null,
      "timestamp": 1737072382279,
      "prediction_price": -0.0005235
    },
    {
      "symbol": "TIA/USDC:USDC",
      "funding_rate": 1.25e-05,
      "funding_rate_pct": 0.00125,
      "datetime": null,
      "timestamp": 1737072382279,
      "prediction_price": 0.00046442
    },
    {
      "symbol": "BLUR/USDC:USDC",
      "funding_rate": 1.25e-05,
      "funding_rate_pct": 0.00125,
      "datetime": null,
      "timestamp": 1737072382279,
      "prediction_price": -0.00021826
    },
    {
      "symbol": "POLYX/USDC:USDC",
      "funding_rate": 1.25e-05,
      "funding_rate_pct": 0.00125,
      "datetime": null,
      "timestamp": 1737072382279,
      "prediction_price": 0.0
    },
    {
      "symbol": "BIGTIME/USDC:USDC",
      "funding_rate": 1.25e-05,
      "funding_rate_pct": 0.00125,
      "datetime": null,
      "timestamp": 1737072382279,
      "prediction_price": 0.0
    },
    {
      "symbol": "REQ/USDC:USDC",
      "funding_rate": 1.25e-05,
      "funding_rate_pct": 0.00125,
      "datetime": null,
      "timestamp": 1737072382279,
      "prediction_price": 0.0
    },
    {
      "symbol": "BNT/USDC:USDC",
      "funding_rate": 1.25e-05,
      "funding_rate_pct": 0.00125,
      "datetime": null,
      "timestamp": 1737072382279,
      "prediction_price": 0.0
    },
    {
      "symbol": "ARK/USDC:USDC",
      "funding_rate": 1.25e-05,
      "funding_rate_pct": 0.00125,
      "datetime": null,
      "timestamp": 1737072382279,
      "prediction_price": 0.0
    },
    {
      "symbol": "OGN/USDC:USDC",
      "funding_rate": 1.25e-05,
      "funding_rate_pct": 0.00125,
      "datetime": null,
      "timestamp": 1737072382279,
      "prediction_price": 0.0
    },
    {
      "symbol": "TNSR/USDC:USDC",
      "funding_rate": 8.5e-06,
      "funding_rate_pct": 0.00085,
      "datetime": null,
      "timestamp": 1737072382279,
      "prediction_price": -0.00064685
    },
    {
      "symbol": "RDNT/USDC:USDC",
      "funding_rate": 7.79e-06,
      "funding_rate_pct": 0.000779,
      "datetime": null,
      "timestamp": 1737072382279,
      "prediction_price": -0.00039471
    },
    {
      "symbol": "IO/USDC:USDC",
      "funding_rate": 3.15e-06,
      "funding_rate_pct": 0.000315,
      "datetime": null,
      "timestamp": 1737072382279,
      "prediction_price": -6.573e-05
    },
    {
      "symbol": "TURBO/USDC:USDC",
      "funding_rate": -2.49e-06,
      "funding_rate_pct": -0.000249,
      "datetime": null,
      "timestamp": 1737072382279,
      "prediction_price": -0.00062704
    }
  ]
}