{
  "timestamp": "20250129_192228",
  "datetime": "2025-01-29T19:22:28.210474",
  "total_markets": 166,
  "statistics": {
    "highest_rate": {
      "symbol": "RUNE/USDC:USDC",
      "rate": -6.473e-05,
      "rate_pct": -0.006473
    },
    "lowest_rate": {
      "symbol": "ADA/USDC:USDC",
      "rate": 1.46e-06,
      "rate_pct": 0.000146
    },
    "mean_rate": 9.272951807228918e-06,
    "median_rate": 1.25e-05
  },
  "rates": [
    {
      "symbol": "RUNE/USDC:USDC",
      "funding_rate": -6.473e-05,
      "funding_rate_pct": -0.006473,
      "datetime": null,
      "timestamp": 1738158557440,
      "prediction_price": -0.000873
    },
    {
      "symbol": "XLM/USDC:USDC",
      "funding_rate": -6.147e-05,
      "funding_rate_pct": -0.0061470000000000006,
      "datetime": null,
      "timestamp": 1738158557440,
      "prediction_price": -0.00119355
    },
    {
      "symbol": "USTC/USDC:USDC",
      "funding_rate": -4.59e-05,
      "funding_rate_pct": -0.0045899999999999995,
      "datetime": null,
      "timestamp": 1738158557440,
      "prediction_price": -0.00042499
    },
    {
      "symbol": "MOVE/USDC:USDC",
      "funding_rate": -3.968e-05,
      "funding_rate_pct": -0.003968,
      "datetime": null,
      "timestamp": 1738158557440,
      "prediction_price": -0.00067844
    },
    {
      "symbol": "ZK/USDC:USDC",
      "funding_rate": 3.074e-05,
      "funding_rate_pct": 0.003074,
      "datetime": null,
      "timestamp": 1738158557440,
      "prediction_price": 0.00088398
    },
    {
      "symbol": "TRX/USDC:USDC",
      "funding_rate": -2.995e-05,
      "funding_rate_pct": -0.002995,
      "datetime": null,
      "timestamp": 1738158557440,
      "prediction_price": -0.00082346
    },
    {
      "symbol": "GMT/USDC:USDC",
      "funding_rate": -2.912e-05,
      "funding_rate_pct": -0.002912,
      "datetime": null,
      "timestamp": 1738158557440,
      "prediction_price": -0.00027697
    },
    {
      "symbol": "CELO/USDC:USDC",
      "funding_rate": -2.354e-05,
      "funding_rate_pct": -0.002354,
      "datetime": null,
      "timestamp": 1738158557440,
      "prediction_price": -0.00076827
    },
    {
      "symbol": "PENDLE/USDC:USDC",
      "funding_rate": -1.992e-05,
      "funding_rate_pct": -0.001992,
      "datetime": null,
      "timestamp": 1738158557440,
      "prediction_price": -0.00056246
    },
    {
      "symbol": "RENDER/USDC:USDC",
      "funding_rate": 1.617e-05,
      "funding_rate_pct": 0.001617,
      "datetime": null,
      "timestamp": 1738158557440,
      "prediction_price": 0.00112272
    },
    {
      "symbol": "POPCAT/USDC:USDC",
      "funding_rate": 1.25e-05,
      "funding_rate_pct": 0.00125,
      "datetime": null,
      "timestamp": 1738158557440,
      "prediction_price": 0.0
    },
    {
      "symbol": "OMNI/USDC:USDC",
      "funding_rate": 1.25e-05,
      "funding_rate_pct": 0.00125,
      "datetime": null,
      "timestamp": 1738158557440,
      "prediction_price": -0.00062222
    },
    {
      "symbol": "HBAR/USDC:USDC",
      "funding_rate": 1.25e-05,
      "funding_rate_pct": 0.00125,
      "datetime": null,
      "timestamp": 1738158557440,
      "prediction_price": 0.00041481
    },
    {
      "symbol": "MERL/USDC:USDC",
      "funding_rate": 1.25e-05,
      "funding_rate_pct": 0.00125,
      "datetime": null,
      "timestamp": 1738158557440,
      "prediction_price": 0.0
    },
    {
      "symbol": "EIGEN/USDC:USDC",
      "funding_rate": 1.25e-05,
      "funding_rate_pct": 0.00125,
      "datetime": null,
      "timestamp": 1738158557440,
      "prediction_price": 0.00073725
    },
    {
      "symbol": "SAGA/USDC:USDC",
      "funding_rate": 1.25e-05,
      "funding_rate_pct": 0.00125,
      "datetime": null,
      "timestamp": 1738158557440,
      "prediction_price": 0.0
    },
    {
      "symbol": "TNSR/USDC:USDC",
      "funding_rate": 1.25e-05,
      "funding_rate_pct": 0.00125,
      "datetime": null,
      "timestamp": 1738158557440,
      "prediction_price": -0.00031521
    },
    {
      "symbol": "REZ/USDC:USDC",
      "funding_rate": 1.25e-05,
      "funding_rate_pct": 0.00125,
      "datetime": null,
      "timestamp": 1738158557440,
      "prediction_price": -0.00110132
    },
    {
      "symbol": "MNT/USDC:USDC",
      "funding_rate": 1.25e-05,
      "funding_rate_pct": 0.00125,
      "datetime": null,
      "timestamp": 1738158557440,
      "prediction_price": -0.00040232
    },
    {
      "symbol": "ETHFI/USDC:USDC",
      "funding_rate": 1.25e-05,
      "funding_rate_pct": 0.00125,
      "datetime": null,
      "timestamp": 1738158557440,
      "prediction_price": 0.00042553
    },
    {
      "symbol": "BOME/USDC:USDC",
      "funding_rate": 1.25e-05,
      "funding_rate_pct": 0.00125,
      "datetime": null,
      "timestamp": 1738158557440,
      "prediction_price": 0.0
    },
    {
      "symbol": "kFLOKI/USDC:USDC",
      "funding_rate": 1.25e-05,
      "funding_rate_pct": 0.00125,
      "datetime": null,
      "timestamp": 1738158557440,
      "prediction_price": 0.0
    },
    {
      "symbol": "MYRO/USDC:USDC",
      "funding_rate": 1.25e-05,
      "funding_rate_pct": 0.00125,
      "datetime": null,
      "timestamp": 1738158557440,
      "prediction_price": 9.724e-05
    },
    {
      "symbol": "NTRN/USDC:USDC",
      "funding_rate": 1.25e-05,
      "funding_rate_pct": 0.00125,
      "datetime": null,
      "timestamp": 1738158557440,
      "prediction_price": 0.0
    },
    {
      "symbol": "TAO/USDC:USDC",
      "funding_rate": 1.25e-05,
      "funding_rate_pct": 0.00125,
      "datetime": null,
      "timestamp": 1738158557440,
      "prediction_price": 0.00082763
    },
    {
      "symbol": "AR/USDC:USDC",
      "funding_rate": 1.25e-05,
      "funding_rate_pct": 0.00125,
      "datetime": null,
      "timestamp": 1738158557440,
      "prediction_price": 5.525e-05
    },
    {
      "symbol": "TURBO/USDC:USDC",
      "funding_rate": 1.25e-05,
      "funding_rate_pct": 0.00125,
      "datetime": null,
      "timestamp": 1738158557440,
      "prediction_price": 0.0
    },
    {
      "symbol": "MAV/USDC:USDC",
      "funding_rate": 1.25e-05,
      "funding_rate_pct": 0.00125,
      "datetime": null,
      "timestamp": 1738158557440,
      "prediction_price": 0.0
    },
    {
      "symbol": "WIF/USDC:USDC",
      "funding_rate": 1.25e-05,
      "funding_rate_pct": 0.00125,
      "datetime": null,
      "timestamp": 1738158557440,
      "prediction_price": -0.00056315
    },
    {
      "symbol": "CAKE/USDC:USDC",
      "funding_rate": 1.25e-05,
      "funding_rate_pct": 0.00125,
      "datetime": null,
      "timestamp": 1738158557440,
      "prediction_price": 0.0006884
    },
    {
      "symbol": "PEOPLE/USDC:USDC",
      "funding_rate": 1.25e-05,
      "funding_rate_pct": 0.00125,
      "datetime": null,
      "timestamp": 1738158557440,
      "prediction_price": 0.0
    },
    {
      "symbol": "ENS/USDC:USDC",
      "funding_rate": 1.25e-05,
      "funding_rate_pct": 0.00125,
      "datetime": null,
      "timestamp": 1738158557440,
      "prediction_price": 0.0
    },
    {
      "symbol": "ETC/USDC:USDC",
      "funding_rate": 1.25e-05,
      "funding_rate_pct": 0.00125,
      "datetime": null,
      "timestamp": 1738158557440,
      "prediction_price": -0.0005963
    },
    {
      "symbol": "XAI/USDC:USDC",
      "funding_rate": 1.25e-05,
      "funding_rate_pct": 0.00125,
      "datetime": null,
      "timestamp": 1738158557440,
      "prediction_price": 0.00013099
    },
    {
      "symbol": "MANTA/USDC:USDC",
      "funding_rate": 1.25e-05,
      "funding_rate_pct": 0.00125,
      "datetime": null,
      "timestamp": 1738158557440,
      "prediction_price": -0.00045991
    },
    {
      "symbol": "UMA/USDC:USDC",
      "funding_rate": 1.25e-05,
      "funding_rate_pct": 0.00125,
      "datetime": null,
      "timestamp": 1738158557440,
      "prediction_price": 0.0
    },
    {
      "symbol": "ONDO/USDC:USDC",
      "funding_rate": 1.25e-05,
      "funding_rate_pct": 0.00125,
      "datetime": null,
      "timestamp": 1738158557440,
      "prediction_price": 0.00056821
    },
    {
      "symbol": "ALT/USDC:USDC",
      "funding_rate": 1.25e-05,
      "funding_rate_pct": 0.00125,
      "datetime": null,
      "timestamp": 1738158557440,
      "prediction_price": -0.00019365
    },
    {
      "symbol": "DYM/USDC:USDC",
      "funding_rate": 1.25e-05,
      "funding_rate_pct": 0.00125,
      "datetime": null,
      "timestamp": 1738158557440,
      "prediction_price": 0.0
    },
    {
      "symbol": "MAVIA/USDC:USDC",
      "funding_rate": 1.25e-05,
      "funding_rate_pct": 0.00125,
      "datetime": null,
      "timestamp": 1738158557440,
      "prediction_price": 0.0
    },
    {
      "symbol": "W/USDC:USDC",
      "funding_rate": 1.25e-05,
      "funding_rate_pct": 0.00125,
      "datetime": null,
      "timestamp": 1738158557440,
      "prediction_price": 0.0
    },
    {
      "symbol": "STRK/USDC:USDC",
      "funding_rate": 1.25e-05,
      "funding_rate_pct": 0.00125,
      "datetime": null,
      "timestamp": 1738158557440,
      "prediction_price": 0.0
    },
    {
      "symbol": "PIXEL/USDC:USDC",
      "funding_rate": 1.25e-05,
      "funding_rate_pct": 0.00125,
      "datetime": null,
      "timestamp": 1738158557440,
      "prediction_price": 0.0
    },
    {
      "symbol": "AI/USDC:USDC",
      "funding_rate": 1.25e-05,
      "funding_rate_pct": 0.00125,
      "datetime": null,
      "timestamp": 1738158557440,
      "prediction_price": 0.0007989
    },
    {
      "symbol": "NOT/USDC:USDC",
      "funding_rate": 1.25e-05,
      "funding_rate_pct": 0.00125,
      "datetime": null,
      "timestamp": 1738158557440,
      "prediction_price": -0.00023663
    },
    {
      "symbol": "MEW/USDC:USDC",
      "funding_rate": 1.25e-05,
      "funding_rate_pct": 0.00125,
      "datetime": null,
      "timestamp": 1738158557440,
      "prediction_price": 0.0
    },
    {
      "symbol": "BRETT/USDC:USDC",
      "funding_rate": 1.25e-05,
      "funding_rate_pct": 0.00125,
      "datetime": null,
      "timestamp": 1738158557440,
      "prediction_price": 0.00034849
    },
    {
      "symbol": "HYPE/USDC:USDC",
      "funding_rate": 1.25e-05,
      "funding_rate_pct": 0.00125,
      "datetime": null,
      "timestamp": 1738158557440,
      "prediction_price": 0.0
    },
    {
      "symbol": "VIRTUAL/USDC:USDC",
      "funding_rate": 1.25e-05,
      "funding_rate_pct": 0.00125,
      "datetime": null,
      "timestamp": 1738158557440,
      "prediction_price": 0.00025865
    },
    {
      "symbol": "PENGU/USDC:USDC",
      "funding_rate": 1.25e-05,
      "funding_rate_pct": 0.00125,
      "datetime": null,
      "timestamp": 1738158557440,
      "prediction_price": -0.00063068
    },
    {
      "symbol": "FARTCOIN/USDC:USDC",
      "funding_rate": 1.25e-05,
      "funding_rate_pct": 0.00125,
      "datetime": null,
      "timestamp": 1738158557440,
      "prediction_price": -0.00237642
    },
    {
      "symbol": "AI16Z/USDC:USDC",
      "funding_rate": 1.25e-05,
      "funding_rate_pct": 0.00125,
      "datetime": null,
      "timestamp": 1738158557440,
      "prediction_price": 0.00115236
    },
    {
      "symbol": "AIXBT/USDC:USDC",
      "funding_rate": 1.25e-05,
      "funding_rate_pct": 0.00125,
      "datetime": null,
      "timestamp": 1738158557440,
      "prediction_price": 0.00040929
    },
    {
      "symbol": "ZEREBRO/USDC:USDC",
      "funding_rate": 1.25e-05,
      "funding_rate_pct": 0.00125,
      "datetime": null,
      "timestamp": 1738158557440,
      "prediction_price": 0.00032805
    },
    {
      "symbol": "BIO/USDC:USDC",
      "funding_rate": 1.25e-05,
      "funding_rate_pct": 0.00125,
      "datetime": null,
      "timestamp": 1738158557440,
      "prediction_price": 0.0
    },
    {
      "symbol": "GRIFFAIN/USDC:USDC",
      "funding_rate": 1.25e-05,
      "funding_rate_pct": 0.00125,
      "datetime": null,
      "timestamp": 1738158557440,
      "prediction_price": 0.0
    },
    {
      "symbol": "SPX/USDC:USDC",
      "funding_rate": 1.25e-05,
      "funding_rate_pct": 0.00125,
      "datetime": null,
      "timestamp": 1738158557440,
      "prediction_price": 0.0001956
    },
    {
      "symbol": "S/USDC:USDC",
      "funding_rate": 1.25e-05,
      "funding_rate_pct": 0.00125,
      "datetime": null,
      "timestamp": 1738158557440,
      "prediction_price": 5.194e-05
    },
    {
      "symbol": "MORPHO/USDC:USDC",
      "funding_rate": 1.25e-05,
      "funding_rate_pct": 0.00125,
      "datetime": null,
      "timestamp": 1738158557440,
      "prediction_price": 4.259e-05
    },
    {
      "symbol": "TRUMP/USDC:USDC",
      "funding_rate": 1.25e-05,
      "funding_rate_pct": 0.00125,
      "datetime": null,
      "timestamp": 1738158557440,
      "prediction_price": -5.429e-05
    },
    {
      "symbol": "MELANIA/USDC:USDC",
      "funding_rate": 1.25e-05,
      "funding_rate_pct": 0.00125,
      "datetime": null,
      "timestamp": 1738158557440,
      "prediction_price": 0.00034722
    },
    {
      "symbol": "ANIME/USDC:USDC",
      "funding_rate": 1.25e-05,
      "funding_rate_pct": 0.00125,
      "datetime": null,
      "timestamp": 1738158557440,
      "prediction_price": 0.0
    },
    {
      "symbol": "VINE/USDC:USDC",
      "funding_rate": 1.25e-05,
      "funding_rate_pct": 0.00125,
      "datetime": null,
      "timestamp": 1738158557440,
      "prediction_price": -0.00115115
    },
    {
      "symbol": "ME/USDC:USDC",
      "funding_rate": 1.25e-05,
      "funding_rate_pct": 0.00125,
      "datetime": null,
      "timestamp": 1738158557440,
      "prediction_price": 0.0
    },
    {
      "symbol": "ALGO/USDC:USDC",
      "funding_rate": 1.25e-05,
      "funding_rate_pct": 0.00125,
      "datetime": null,
      "timestamp": 1738158557440,
      "prediction_price": 0.00011925
    },
    {
      "symbol": "LISTA/USDC:USDC",
      "funding_rate": 1.25e-05,
      "funding_rate_pct": 0.00125,
      "datetime": null,
      "timestamp": 1738158557440,
      "prediction_price": 0.0
    },
    {
      "symbol": "IOTA/USDC:USDC",
      "funding_rate": 1.25e-05,
      "funding_rate_pct": 0.00125,
      "datetime": null,
      "timestamp": 1738158557440,
      "prediction_price": 0.0001731
    },
    {
      "symbol": "ETH/USDC:USDC",
      "funding_rate": 1.25e-05,
      "funding_rate_pct": 0.00125,
      "datetime": null,
      "timestamp": 1738158557440,
      "prediction_price": -6.451e-05
    },
    {
      "symbol": "kDOGS/USDC:USDC",
      "funding_rate": 1.25e-05,
      "funding_rate_pct": 0.00125,
      "datetime": null,
      "timestamp": 1738158557440,
      "prediction_price": -0.00030865
    },
    {
      "symbol": "POL/USDC:USDC",
      "funding_rate": 1.25e-05,
      "funding_rate_pct": 0.00125,
      "datetime": null,
      "timestamp": 1738158557440,
      "prediction_price": -0.000472
    },
    {
      "symbol": "CATI/USDC:USDC",
      "funding_rate": 1.25e-05,
      "funding_rate_pct": 0.00125,
      "datetime": null,
      "timestamp": 1738158557440,
      "prediction_price": -0.00040018
    },
    {
      "symbol": "HMSTR/USDC:USDC",
      "funding_rate": 1.25e-05,
      "funding_rate_pct": 0.00125,
      "datetime": null,
      "timestamp": 1738158557440,
      "prediction_price": 0.0
    },
    {
      "symbol": "SCR/USDC:USDC",
      "funding_rate": 1.25e-05,
      "funding_rate_pct": 0.00125,
      "datetime": null,
      "timestamp": 1738158557440,
      "prediction_price": -3.166e-05
    },
    {
      "symbol": "NEIROETH/USDC:USDC",
      "funding_rate": 1.25e-05,
      "funding_rate_pct": 0.00125,
      "datetime": null,
      "timestamp": 1738158557440,
      "prediction_price": 0.00040798
    },
    {
      "symbol": "kNEIRO/USDC:USDC",
      "funding_rate": 1.25e-05,
      "funding_rate_pct": 0.00125,
      "datetime": null,
      "timestamp": 1738158557440,
      "prediction_price": -0.00034797
    },
    {
      "symbol": "GOAT/USDC:USDC",
      "funding_rate": 1.25e-05,
      "funding_rate_pct": 0.00125,
      "datetime": null,
      "timestamp": 1738158557440,
      "prediction_price": 0.00026021
    },
    {
      "symbol": "MOODENG/USDC:USDC",
      "funding_rate": 1.25e-05,
      "funding_rate_pct": 0.00125,
      "datetime": null,
      "timestamp": 1738158557440,
      "prediction_price": 0.0
    },
    {
      "symbol": "GRASS/USDC:USDC",
      "funding_rate": 1.25e-05,
      "funding_rate_pct": 0.00125,
      "datetime": null,
      "timestamp": 1738158557440,
      "prediction_price": 0.0
    },
    {
      "symbol": "PURR/USDC:USDC",
      "funding_rate": 1.25e-05,
      "funding_rate_pct": 0.00125,
      "datetime": null,
      "timestamp": 1738158557440,
      "prediction_price": 0.00323699
    },
    {
      "symbol": "PNUT/USDC:USDC",
      "funding_rate": 1.25e-05,
      "funding_rate_pct": 0.00125,
      "datetime": null,
      "timestamp": 1738158557440,
      "prediction_price": -0.00023641
    },
    {
      "symbol": "CHILLGUY/USDC:USDC",
      "funding_rate": 1.25e-05,
      "funding_rate_pct": 0.00125,
      "datetime": null,
      "timestamp": 1738158557440,
      "prediction_price": 0.0
    },
    {
      "symbol": "SAND/USDC:USDC",
      "funding_rate": 1.25e-05,
      "funding_rate_pct": 0.00125,
      "datetime": null,
      "timestamp": 1738158557440,
      "prediction_price": 0.0
    },
    {
      "symbol": "ACE/USDC:USDC",
      "funding_rate": 1.25e-05,
      "funding_rate_pct": 0.00125,
      "datetime": null,
      "timestamp": 1738158557440,
      "prediction_price": 0.0
    },
    {
      "symbol": "VVV/USDC:USDC",
      "funding_rate": 1.25e-05,
      "funding_rate_pct": 0.00125,
      "datetime": null,
      "timestamp": 1738158557440,
      "prediction_price": -0.00054995
    },
    {
      "symbol": "JTO/USDC:USDC",
      "funding_rate": 1.25e-05,
      "funding_rate_pct": 0.00125,
      "datetime": null,
      "timestamp": 1738158557440,
      "prediction_price": -0.00042477
    },
    {
      "symbol": "GMX/USDC:USDC",
      "funding_rate": 1.25e-05,
      "funding_rate_pct": 0.00125,
      "datetime": null,
      "timestamp": 1738158557440,
      "prediction_price": 0.00031165
    },
    {
      "symbol": "XRP/USDC:USDC",
      "funding_rate": 1.25e-05,
      "funding_rate_pct": 0.00125,
      "datetime": null,
      "timestamp": 1738158557440,
      "prediction_price": 0.0001966
    },
    {
      "symbol": "BCH/USDC:USDC",
      "funding_rate": 1.25e-05,
      "funding_rate_pct": 0.00125,
      "datetime": null,
      "timestamp": 1738158557440,
      "prediction_price": 0.00043945
    },
    {
      "symbol": "APT/USDC:USDC",
      "funding_rate": 1.25e-05,
      "funding_rate_pct": 0.00125,
      "datetime": null,
      "timestamp": 1738158557440,
      "prediction_price": -9.629e-05
    },
    {
      "symbol": "AAVE/USDC:USDC",
      "funding_rate": 1.25e-05,
      "funding_rate_pct": 0.00125,
      "datetime": null,
      "timestamp": 1738158557440,
      "prediction_price": 0.0
    },
    {
      "symbol": "MKR/USDC:USDC",
      "funding_rate": 1.25e-05,
      "funding_rate_pct": 0.00125,
      "datetime": null,
      "timestamp": 1738158557440,
      "prediction_price": 2.691e-05
    },
    {
      "symbol": "WLD/USDC:USDC",
      "funding_rate": 1.25e-05,
      "funding_rate_pct": 0.00125,
      "datetime": null,
      "timestamp": 1738158557440,
      "prediction_price": -0.00011872
    },
    {
      "symbol": "FXS/USDC:USDC",
      "funding_rate": 1.25e-05,
      "funding_rate_pct": 0.00125,
      "datetime": null,
      "timestamp": 1738158557440,
      "prediction_price": -0.00035562
    },
    {
      "symbol": "HPOS/USDC:USDC",
      "funding_rate": 1.25e-05,
      "funding_rate_pct": 0.00125,
      "datetime": null,
      "timestamp": 1738158557440,
      "prediction_price": 0.0
    },
    {
      "symbol": "RLB/USDC:USDC",
      "funding_rate": 1.25e-05,
      "funding_rate_pct": 0.00125,
      "datetime": null,
      "timestamp": 1738158557440,
      "prediction_price": 0.0
    },
    {
      "symbol": "YGG/USDC:USDC",
      "funding_rate": 1.25e-05,
      "funding_rate_pct": 0.00125,
      "datetime": null,
      "timestamp": 1738158557440,
      "prediction_price": 1.317e-05
    },
    {
      "symbol": "UNI/USDC:USDC",
      "funding_rate": 1.25e-05,
      "funding_rate_pct": 0.00125,
      "datetime": null,
      "timestamp": 1738158557440,
      "prediction_price": -0.00013558
    },
    {
      "symbol": "CYBER/USDC:USDC",
      "funding_rate": 1.25e-05,
      "funding_rate_pct": 0.00125,
      "datetime": null,
      "timestamp": 1738158557440,
      "prediction_price": -0.00013478
    },
    {
      "symbol": "ZRO/USDC:USDC",
      "funding_rate": 1.25e-05,
      "funding_rate_pct": 0.00125,
      "datetime": null,
      "timestamp": 1738158557440,
      "prediction_price": 5.785e-05
    },
    {
      "symbol": "DOT/USDC:USDC",
      "funding_rate": 1.25e-05,
      "funding_rate_pct": 0.00125,
      "datetime": null,
      "timestamp": 1738158557440,
      "prediction_price": -0.00041145
    },
    {
      "symbol": "BANANA/USDC:USDC",
      "funding_rate": 1.25e-05,
      "funding_rate_pct": 0.00125,
      "datetime": null,
      "timestamp": 1738158557440,
      "prediction_price": 0.0
    },
    {
      "symbol": "SNX/USDC:USDC",
      "funding_rate": 1.25e-05,
      "funding_rate_pct": 0.00125,
      "datetime": null,
      "timestamp": 1738158557440,
      "prediction_price": -0.00014941
    },
    {
      "symbol": "CFX/USDC:USDC",
      "funding_rate": 1.25e-05,
      "funding_rate_pct": 0.00125,
      "datetime": null,
      "timestamp": 1738158557440,
      "prediction_price": -5.517e-05
    },
    {
      "symbol": "FTT/USDC:USDC",
      "funding_rate": 1.25e-05,
      "funding_rate_pct": 0.00125,
      "datetime": null,
      "timestamp": 1738158557440,
      "prediction_price": 0.0
    },
    {
      "symbol": "STX/USDC:USDC",
      "funding_rate": 1.25e-05,
      "funding_rate_pct": 0.00125,
      "datetime": null,
      "timestamp": 1738158557440,
      "prediction_price": -0.00056749
    },
    {
      "symbol": "ATOM/USDC:USDC",
      "funding_rate": 1.25e-05,
      "funding_rate_pct": 0.00125,
      "datetime": null,
      "timestamp": 1738158557440,
      "prediction_price": 0.0
    },
    {
      "symbol": "DYDX/USDC:USDC",
      "funding_rate": 1.25e-05,
      "funding_rate_pct": 0.00125,
      "datetime": null,
      "timestamp": 1738158557440,
      "prediction_price": -0.00014964
    },
    {
      "symbol": "SOL/USDC:USDC",
      "funding_rate": 1.25e-05,
      "funding_rate_pct": 0.00125,
      "datetime": null,
      "timestamp": 1738158557440,
      "prediction_price": 0.00013227
    },
    {
      "symbol": "AVAX/USDC:USDC",
      "funding_rate": 1.25e-05,
      "funding_rate_pct": 0.00125,
      "datetime": null,
      "timestamp": 1738158557440,
      "prediction_price": -3.086e-05
    },
    {
      "symbol": "BNB/USDC:USDC",
      "funding_rate": 1.25e-05,
      "funding_rate_pct": 0.00125,
      "datetime": null,
      "timestamp": 1738158557440,
      "prediction_price": -0.00045195
    },
    {
      "symbol": "APE/USDC:USDC",
      "funding_rate": 1.25e-05,
      "funding_rate_pct": 0.00125,
      "datetime": null,
      "timestamp": 1738158557440,
      "prediction_price": -0.00022173
    },
    {
      "symbol": "OP/USDC:USDC",
      "funding_rate": 1.25e-05,
      "funding_rate_pct": 0.00125,
      "datetime": null,
      "timestamp": 1738158557440,
      "prediction_price": -0.00063251
    },
    {
      "symbol": "LTC/USDC:USDC",
      "funding_rate": 1.25e-05,
      "funding_rate_pct": 0.00125,
      "datetime": null,
      "timestamp": 1738158557440,
      "prediction_price": -0.00012699
    },
    {
      "symbol": "ARB/USDC:USDC",
      "funding_rate": 1.25e-05,
      "funding_rate_pct": 0.00125,
      "datetime": null,
      "timestamp": 1738158557440,
      "prediction_price": -0.00068396
    },
    {
      "symbol": "INJ/USDC:USDC",
      "funding_rate": 1.25e-05,
      "funding_rate_pct": 0.00125,
      "datetime": null,
      "timestamp": 1738158557440,
      "prediction_price": -0.00010002
    },
    {
      "symbol": "SUI/USDC:USDC",
      "funding_rate": 1.25e-05,
      "funding_rate_pct": 0.00125,
      "datetime": null,
      "timestamp": 1738158557440,
      "prediction_price": -0.00012125
    },
    {
      "symbol": "kPEPE/USDC:USDC",
      "funding_rate": 1.25e-05,
      "funding_rate_pct": 0.00125,
      "datetime": null,
      "timestamp": 1738158557440,
      "prediction_price": -8.143e-05
    },
    {
      "symbol": "CRV/USDC:USDC",
      "funding_rate": 1.25e-05,
      "funding_rate_pct": 0.00125,
      "datetime": null,
      "timestamp": 1738158557440,
      "prediction_price": 0.0
    },
    {
      "symbol": "LDO/USDC:USDC",
      "funding_rate": 1.25e-05,
      "funding_rate_pct": 0.00125,
      "datetime": null,
      "timestamp": 1738158557440,
      "prediction_price": -0.00014611
    },
    {
      "symbol": "LINK/USDC:USDC",
      "funding_rate": 1.25e-05,
      "funding_rate_pct": 0.00125,
      "datetime": null,
      "timestamp": 1738158557440,
      "prediction_price": -0.00017555
    },
    {
      "symbol": "GALA/USDC:USDC",
      "funding_rate": 1.25e-05,
      "funding_rate_pct": 0.00125,
      "datetime": null,
      "timestamp": 1738158557440,
      "prediction_price": 0.0
    },
    {
      "symbol": "TRB/USDC:USDC",
      "funding_rate": 1.25e-05,
      "funding_rate_pct": 0.00125,
      "datetime": null,
      "timestamp": 1738158557440,
      "prediction_price": 0.0
    },
    {
      "symbol": "STG/USDC:USDC",
      "funding_rate": 1.25e-05,
      "funding_rate_pct": 0.00125,
      "datetime": null,
      "timestamp": 1738158557440,
      "prediction_price": 0.0
    },
    {
      "symbol": "FIL/USDC:USDC",
      "funding_rate": 1.25e-05,
      "funding_rate_pct": 0.00125,
      "datetime": null,
      "timestamp": 1738158557440,
      "prediction_price": -0.00011264
    },
    {
      "symbol": "ZEN/USDC:USDC",
      "funding_rate": 1.25e-05,
      "funding_rate_pct": 0.00125,
      "datetime": null,
      "timestamp": 1738158557440,
      "prediction_price": 0.0
    },
    {
      "symbol": "ILV/USDC:USDC",
      "funding_rate": 1.25e-05,
      "funding_rate_pct": 0.00125,
      "datetime": null,
      "timestamp": 1738158557440,
      "prediction_price": 0.0
    },
    {
      "symbol": "NEO/USDC:USDC",
      "funding_rate": 1.25e-05,
      "funding_rate_pct": 0.00125,
      "datetime": null,
      "timestamp": 1738158557440,
      "prediction_price": -6.216e-05
    },
    {
      "symbol": "BADGER/USDC:USDC",
      "funding_rate": 1.25e-05,
      "funding_rate_pct": 0.00125,
      "datetime": null,
      "timestamp": 1738158557440,
      "prediction_price": 0.00039131
    },
    {
      "symbol": "ORDI/USDC:USDC",
      "funding_rate": 1.25e-05,
      "funding_rate_pct": 0.00125,
      "datetime": null,
      "timestamp": 1738158557440,
      "prediction_price": -0.00020728
    },
    {
      "symbol": "MEME/USDC:USDC",
      "funding_rate": 1.25e-05,
      "funding_rate_pct": 0.00125,
      "datetime": null,
      "timestamp": 1738158557440,
      "prediction_price": 0.0
    },
    {
      "symbol": "NEAR/USDC:USDC",
      "funding_rate": 1.25e-05,
      "funding_rate_pct": 0.00125,
      "datetime": null,
      "timestamp": 1738158557440,
      "prediction_price": 0.0
    },
    {
      "symbol": "FET/USDC:USDC",
      "funding_rate": 1.25e-05,
      "funding_rate_pct": 0.00125,
      "datetime": null,
      "timestamp": 1738158557440,
      "prediction_price": 9.379e-05
    },
    {
      "symbol": "OGN/USDC:USDC",
      "funding_rate": 1.25e-05,
      "funding_rate_pct": 0.00125,
      "datetime": null,
      "timestamp": 1738158557440,
      "prediction_price": 0.0
    },
    {
      "symbol": "GAS/USDC:USDC",
      "funding_rate": 1.25e-05,
      "funding_rate_pct": 0.00125,
      "datetime": null,
      "timestamp": 1738158557440,
      "prediction_price": 0.0
    },
    {
      "symbol": "POLYX/USDC:USDC",
      "funding_rate": 1.25e-05,
      "funding_rate_pct": 0.00125,
      "datetime": null,
      "timestamp": 1738158557440,
      "prediction_price": -0.00038237
    },
    {
      "symbol": "MINA/USDC:USDC",
      "funding_rate": 1.25e-05,
      "funding_rate_pct": 0.00125,
      "datetime": null,
      "timestamp": 1738158557440,
      "prediction_price": -0.00034265
    },
    {
      "symbol": "TON/USDC:USDC",
      "funding_rate": 1.25e-05,
      "funding_rate_pct": 0.00125,
      "datetime": null,
      "timestamp": 1738158557440,
      "prediction_price": 0.0
    },
    {
      "symbol": "kBONK/USDC:USDC",
      "funding_rate": 1.25e-05,
      "funding_rate_pct": 0.00125,
      "datetime": null,
      "timestamp": 1738158557440,
      "prediction_price": 0.0
    },
    {
      "symbol": "SUPER/USDC:USDC",
      "funding_rate": 1.25e-05,
      "funding_rate_pct": 0.00125,
      "datetime": null,
      "timestamp": 1738158557440,
      "prediction_price": -0.00041452
    },
    {
      "symbol": "JUP/USDC:USDC",
      "funding_rate": 1.25e-05,
      "funding_rate_pct": 0.00125,
      "datetime": null,
      "timestamp": 1738158557440,
      "prediction_price": -3.842e-05
    },
    {
      "symbol": "BSV/USDC:USDC",
      "funding_rate": 1.25e-05,
      "funding_rate_pct": 0.00125,
      "datetime": null,
      "timestamp": 1738158557440,
      "prediction_price": 0.0
    },
    {
      "symbol": "BLUR/USDC:USDC",
      "funding_rate": 1.25e-05,
      "funding_rate_pct": 0.00125,
      "datetime": null,
      "timestamp": 1738158557440,
      "prediction_price": 0.0
    },
    {
      "symbol": "ORBS/USDC:USDC",
      "funding_rate": 1.25e-05,
      "funding_rate_pct": 0.00125,
      "datetime": null,
      "timestamp": 1738158557440,
      "prediction_price": 0.0
    },
    {
      "symbol": "kLUNC/USDC:USDC",
      "funding_rate": 1.25e-05,
      "funding_rate_pct": 0.00125,
      "datetime": null,
      "timestamp": 1738158557440,
      "prediction_price": 0.00013486
    },
    {
      "symbol": "KAS/USDC:USDC",
      "funding_rate": 1.25e-05,
      "funding_rate_pct": 0.00125,
      "datetime": null,
      "timestamp": 1738158557440,
      "prediction_price": 0.0
    },
    {
      "symbol": "RSR/USDC:USDC",
      "funding_rate": 1.25e-05,
      "funding_rate_pct": 0.00125,
      "datetime": null,
      "timestamp": 1738158557440,
      "prediction_price": -0.00016154
    },
    {
      "symbol": "BIGTIME/USDC:USDC",
      "funding_rate": 1.25e-05,
      "funding_rate_pct": 0.00125,
      "datetime": null,
      "timestamp": 1738158557440,
      "prediction_price": -0.00013003
    },
    {
      "symbol": "REQ/USDC:USDC",
      "funding_rate": 1.25e-05,
      "funding_rate_pct": 0.00125,
      "datetime": null,
      "timestamp": 1738158557440,
      "prediction_price": 0.0
    },
    {
      "symbol": "BNT/USDC:USDC",
      "funding_rate": 1.25e-05,
      "funding_rate_pct": 0.00125,
      "datetime": null,
      "timestamp": 1738158557440,
      "prediction_price": 0.0
    },
    {
      "symbol": "ARK/USDC:USDC",
      "funding_rate": 1.25e-05,
      "funding_rate_pct": 0.00125,
      "datetime": null,
      "timestamp": 1738158557440,
      "prediction_price": 0.0
    },
    {
      "symbol": "RDNT/USDC:USDC",
      "funding_rate": 1.25e-05,
      "funding_rate_pct": 0.00125,
      "datetime": null,
      "timestamp": 1738158557440,
      "prediction_price": -0.00011498
    },
    {
      "symbol": "PYTH/USDC:USDC",
      "funding_rate": 1.25e-05,
      "funding_rate_pct": 0.00125,
      "datetime": null,
      "timestamp": 1738158557440,
      "prediction_price": -0.00021888
    },
    {
      "symbol": "BLAST/USDC:USDC",
      "funding_rate": -1.188e-05,
      "funding_rate_pct": -0.001188,
      "datetime": null,
      "timestamp": 1738158557440,
      "prediction_price": -0.00055006
    },
    {
      "symbol": "TIA/USDC:USDC",
      "funding_rate": 1.083e-05,
      "funding_rate_pct": 0.001083,
      "datetime": null,
      "timestamp": 1738158557440,
      "prediction_price": -2.319e-05
    },
    {
      "symbol": "BTC/USDC:USDC",
      "funding_rate": 1.075e-05,
      "funding_rate_pct": 0.001075,
      "datetime": null,
      "timestamp": 1738158557440,
      "prediction_price": -0.00079529
    },
    {
      "symbol": "COMP/USDC:USDC",
      "funding_rate": 1.072e-05,
      "funding_rate_pct": 0.001072,
      "datetime": null,
      "timestamp": 1738158557440,
      "prediction_price": 0.0
    },
    {
      "symbol": "ZETA/USDC:USDC",
      "funding_rate": -1.066e-05,
      "funding_rate_pct": -0.0010659999999999999,
      "datetime": null,
      "timestamp": 1738158557440,
      "prediction_price": -0.00023996
    },
    {
      "symbol": "SUSHI/USDC:USDC",
      "funding_rate": 1.029e-05,
      "funding_rate_pct": 0.001029,
      "datetime": null,
      "timestamp": 1738158557440,
      "prediction_price": -0.00091224
    },
    {
      "symbol": "kSHIB/USDC:USDC",
      "funding_rate": 1.015e-05,
      "funding_rate_pct": 0.0010149999999999998,
      "datetime": null,
      "timestamp": 1738158557440,
      "prediction_price": -0.00038678
    },
    {
      "symbol": "SEI/USDC:USDC",
      "funding_rate": -7.06e-06,
      "funding_rate_pct": -0.000706,
      "datetime": null,
      "timestamp": 1738158557440,
      "prediction_price": -0.00067295
    },
    {
      "symbol": "DOGE/USDC:USDC",
      "funding_rate": -6.48e-06,
      "funding_rate_pct": -0.000648,
      "datetime": null,
      "timestamp": 1738158557440,
      "prediction_price": -0.00046432
    },
    {
      "symbol": "USUAL/USDC:USDC",
      "funding_rate": 5.53e-06,
      "funding_rate_pct": 0.000553,
      "datetime": null,
      "timestamp": 1738158557440,
      "prediction_price": -0.00010341
    },
    {
      "symbol": "IO/USDC:USDC",
      "funding_rate": 3.49e-06,
      "funding_rate_pct": 0.000349,
      "datetime": null,
      "timestamp": 1738158557440,
      "prediction_price": 0.0
    },
    {
      "symbol": "IMX/USDC:USDC",
      "funding_rate": 2.96e-06,
      "funding_rate_pct": 0.000296,
      "datetime": null,
      "timestamp": 1738158557440,
      "prediction_price": -0.00092019
    },
    {
      "symbol": "ENA/USDC:USDC",
      "funding_rate": 1.61e-06,
      "funding_rate_pct": 0.000161,
      "datetime": null,
      "timestamp": 1738158557440,
      "prediction_price": -0.00070335
    },
    {
      "symbol": "ADA/USDC:USDC",
      "funding_rate": 1.46e-06,
      "funding_rate_pct": 0.000146,
      "datetime": null,
      "timestamp": 1738158557440,
      "prediction_price": -0.00045566
    }
  ]
}